inepandas/__init__.py
inepandas/client.py
inepandas/data.py
inepandas/exceptions.py
inepandas/metadata.py
inepandas/py.typed
inepandas-0.1.2.dist-info/METADATA
inepandas-0.1.2.dist-info/WHEEL
inepandas-0.1.2.dist-info/licenses/LICENSE
inepandas-0.1.2.dist-info/RECORD
