Metadata-Version: 2.4
Name: inepandas
Version: 0.1.2
Summary: A Python wrapper for the Spanish National Statistics Institute (INE) API
License: MIT
License-File: LICENSE
Keywords: ine,spain,statistics,api,data,pandas
Author: Jonathan Mair jonathan.mair@gmail.com
Requires-Python: >=3.12,<4.0
Classifier: Development Status :: 3 - Alpha
Classifier: Intended Audience :: Developers
Classifier: Intended Audience :: Science/Research
Classifier: License :: OSI Approved :: MIT License
Classifier: Operating System :: OS Independent
Classifier: Programming Language :: Python :: 3
Classifier: Programming Language :: Python :: 3.12
Classifier: Programming Language :: Python :: 3.13
Classifier: Programming Language :: Python :: 3.14
Classifier: Topic :: Scientific/Engineering
Classifier: Topic :: Software Development :: Libraries :: Python Modules
Classifier: Typing :: Typed
Requires-Dist: pandas (>=2.2.0,<3.0.0)
Requires-Dist: requests (>=2.32.0,<3.0.0)
Project-URL: Documentation, https://jonathanmair.github.io/inepandas/inepandas.html
Project-URL: Homepage, https://github.com/JonathanMair/inepandas
Project-URL: Repository, https://github.com/JonathanMair/inepandas
